README.md
arg.c
arg.h
d.h
dparse.h
dparse_tables.h
dparse_tree.c
dparse_tree.h
driver_parsetree.c
dsymtab.h
gram.c
gram.h
gramgram.h
grammar.g.c
lex.c
lex.h
lr.c
lr.h
make_dparser.c
mkdparse.c
mkdparse.h
my.c
parse.c
parse.h
read_binary.c
read_binary.h
sample_parser.c
scan.c
scan.h
setup.py
symtab.c
test_parser.c
util.c
util.h
version.c
write_tables.c
write_tables.h
python/dparser.i
python/dparser.py
python/make_tables.c
python/pydparser.c
python/pydparser.h
python/swigpyrun.h
python/dparser.egg-info/PKG-INFO
python/dparser.egg-info/SOURCES.txt
python/dparser.egg-info/dependency_links.txt
python/dparser.egg-info/top_level.txt