Metadata-Version: 1.0
Name: dparser
Version: 1.31.8
Summary: DParser for Python
Home-page: https://github.com/jplevyak/dparser
Author: John Plevyak
Author-email: jplevyak@gmail.com
License: UNKNOWN
Platform: UNKNOWN
